bidimensional/__init__.py
bidimensional/core/__init__.py
bidimensional/core/coordinate.py
bidimensional/core/lines.py
bidimensional/core/operations.py
bidimensional/functions/__init__.py
bidimensional/functions/spline.py
bidimensional/polygons/__init__.py
bidimensional/polygons/polygon.py
bidimensional/polygons/triangle.py
bidimensional-1.9.1.dist-info/LICENSE
bidimensional-1.9.1.dist-info/METADATA
bidimensional-1.9.1.dist-info/WHEEL
bidimensional-1.9.1.dist-info/top_level.txt
bidimensional-1.9.1.dist-info/RECORD
