Metadata-Version: 2.1
Name: bidimensional
Version: 1.9.1
Summary: A collection of 2D utilities for coordinate representation and manipulation.
Author-email: Paulo Sanchez <dev.szblzpaulo@gmail.com>
Maintainer-email: Paulo Sanchez <dev.szblzpaulo@gmail.com>
License: GNU AFFERO GENERAL PUBLIC LICENSE
Project-URL: Homepage, https://github.com/erlete/bidimensional
Project-URL: Bug Tracker, https://github.com/erlete/bidimensional/issues
Classifier: Intended Audience :: Developers
Classifier: Programming Language :: Python :: 3
Classifier: License :: OSI Approved :: GNU General Public License v3 (GPLv3)
Classifier: Operating System :: OS Independent
Requires-Python: >=3.7.13
License-File: LICENSE
